{
  "timestamp": "2025-10-18T06:08:31.567Z",
  "metrics": {
    "totalKeywords": 127,
    "avgPosition": 18.97,
    "top10Count": 33,
    "top10Percentage": 25.98,
    "top3Count": 6,
    "top3Percentage": 4.72,
    "positionChanges": {
      "improved": 42,
      "declined": 55,
      "stable": 30
    },
    "estimatedTraffic": 14596,
    "categoryStats": {
      "seed": {
        "count": 18,
        "avgPosition": 13.56,
        "top10Count": 9
      },
      "residential": {
        "count": 10,
        "avgPosition": 12.2,
        "top10Count": 7
      },
      "storage": {
        "count": 10,
        "avgPosition": 19.2,
        "top10Count": 3
      },
      "residential_installation": {
        "count": 10,
        "avgPosition": 15.6,
        "top10Count": 4
      },
      "competitive": {
        "count": 9,
        "avgPosition": 20.11,
        "top10Count": 2
      },
      "technical": {
        "count": 10,
        "avgPosition": 22.8,
        "top10Count": 2
      },
      "residential_financing": {
        "count": 10,
        "avgPosition": 18.2,
        "top10Count": 2
      },
      "applications": {
        "count": 10,
        "avgPosition": 22.6,
        "top10Count": 1
      },
      "longtail": {
        "count": 10,
        "avgPosition": 19.9,
        "top10Count": 3
      },
      "legal": {
        "count": 10,
        "avgPosition": 17.7,
        "top10Count": 0
      },
      "regional": {
        "count": 10,
        "avgPosition": 24.8,
        "top10Count": 0
      },
      "regional_residential": {
        "count": 10,
        "avgPosition": 25.4,
        "top10Count": 0
      }
    },
    "segmentStats": {
      "residential": {
        "count": 40,
        "avgPosition": 16.33,
        "top10Count": 18,
        "estimatedTraffic": 8018,
        "top10Percentage": 45
      },
      "storage": {
        "count": 9,
        "avgPosition": 17.11,
        "top10Count": 3,
        "estimatedTraffic": 1381,
        "top10Percentage": 33.33
      },
      "sector-coupling": {
        "count": 2,
        "avgPosition": 9,
        "top10Count": 2,
        "estimatedTraffic": 660,
        "top10Percentage": 100
      },
      "general": {
        "count": 11,
        "avgPosition": 22.09,
        "top10Count": 1,
        "estimatedTraffic": 679,
        "top10Percentage": 9.09
      },
      "agri-pv": {
        "count": 65,
        "avgPosition": 20.63,
        "top10Count": 9,
        "estimatedTraffic": 3859,
        "top10Percentage": 13.85
      }
    },
    "timestamp": "2025-10-18T06:08:31.520Z"
  },
  "positions": {
    "Solaranlage Einfamilienhaus": {
      "keyword": "Solaranlage Einfamilienhaus",
      "position": 6,
      "previousPosition": 8,
      "searchVolume": 4400,
      "competition": 72,
      "difficulty": 60,
      "opportunityScore": 3333,
      "category": "seed",
      "intent": "mixed",
      "segment": "residential",
      "lastUpdated": "2025-10-18T06:08:31.519Z"
    },
    "Photovoltaik mit Speicher": {
      "keyword": "Photovoltaik mit Speicher",
      "position": 7,
      "previousPosition": 9,
      "searchVolume": 4100,
      "competition": 65,
      "difficulty": 58,
      "opportunityScore": 3333,
      "category": "seed",
      "intent": "mixed",
      "segment": "storage",
      "lastUpdated": "2025-10-18T06:08:31.519Z"
    },
    "Solaranlage Eigenheim Kosten": {
      "keyword": "Solaranlage Eigenheim Kosten",
      "position": 1,
      "previousPosition": 1,
      "searchVolume": 4200,
      "competition": 70,
      "difficulty": 62,
      "opportunityScore": 3182,
      "category": "residential",
      "intent": "commercial",
      "segment": "residential",
      "lastUpdated": "2025-10-18T06:08:31.519Z"
    },
    "Solaranlage Eigenheim": {
      "keyword": "Solaranlage Eigenheim",
      "position": 10,
      "previousPosition": 10,
      "searchVolume": 3600,
      "competition": 68,
      "difficulty": 55,
      "opportunityScore": 2927,
      "category": "seed",
      "intent": "mixed",
      "segment": "residential",
      "lastUpdated": "2025-10-18T06:08:31.519Z"
    },
    "Wärmepumpe und Photovoltaik": {
      "keyword": "Wärmepumpe und Photovoltaik",
      "position": 8,
      "previousPosition": 8,
      "searchVolume": 2800,
      "competition": 58,
      "difficulty": 49,
      "opportunityScore": 2617,
      "category": "seed",
      "intent": "mixed",
      "segment": "sector-coupling",
      "lastUpdated": "2025-10-18T06:08:31.519Z"
    },
    "Wärmepumpe Photovoltaik Kombination": {
      "keyword": "Wärmepumpe Photovoltaik Kombination",
      "position": 10,
      "previousPosition": 12,
      "searchVolume": 1600,
      "competition": 42,
      "difficulty": 20,
      "opportunityScore": 2581,
      "category": "storage",
      "intent": "mixed",
      "segment": "sector-coupling",
      "lastUpdated": "2025-10-18T06:08:31.519Z"
    },
    "Solaranlage Einfamilienhaus Kosten": {
      "keyword": "Solaranlage Einfamilienhaus Kosten",
      "position": 1,
      "previousPosition": 2,
      "searchVolume": 2900,
      "competition": 68,
      "difficulty": 55,
      "opportunityScore": 2358,
      "category": "residential",
      "intent": "commercial",
      "segment": "residential",
      "lastUpdated": "2025-10-18T06:08:31.519Z"
    },
    "PV Anlage Hausdach": {
      "keyword": "PV Anlage Hausdach",
      "position": 6,
      "previousPosition": 7,
      "searchVolume": 2500,
      "competition": 58,
      "difficulty": 52,
      "opportunityScore": 2273,
      "category": "seed",
      "intent": "mixed",
      "segment": "residential",
      "lastUpdated": "2025-10-18T06:08:31.519Z"
    },
    "Photovoltaik Eigenverbrauch erhöhen": {
      "keyword": "Photovoltaik Eigenverbrauch erhöhen",
      "position": 9,
      "previousPosition": 6,
      "searchVolume": 2100,
      "competition": 58,
      "difficulty": 47,
      "opportunityScore": 2000,
      "category": "residential_installation",
      "intent": "mixed",
      "segment": "general",
      "lastUpdated": "2025-10-18T06:08:31.519Z"
    },
    "Solarstrom Eigenheim": {
      "keyword": "Solarstrom Eigenheim",
      "position": 7,
      "previousPosition": 9,
      "searchVolume": 2100,
      "competition": 56,
      "difficulty": 50,
      "opportunityScore": 1981,
      "category": "seed",
      "intent": "mixed",
      "segment": "residential",
      "lastUpdated": "2025-10-18T06:08:31.519Z"
    },
    "Agri-PV Umsetzung": {
      "keyword": "Agri-PV Umsetzung",
      "position": 8,
      "previousPosition": 6,
      "searchVolume": 982,
      "competition": 30,
      "difficulty": 21,
      "opportunityScore": 1925,
      "category": "competitive",
      "intent": "mixed",
      "segment": "agri-pv",
      "lastUpdated": "2025-10-18T06:08:31.519Z"
    },
    "Agri-PV": {
      "keyword": "Agri-PV",
      "position": 1,
      "previousPosition": 1,
      "searchVolume": 2900,
      "competition": 75,
      "difficulty": 78,
      "opportunityScore": 1895,
      "category": "seed",
      "intent": "mixed",
      "segment": "agri-pv",
      "lastUpdated": "2025-10-18T06:08:31.519Z"
    },
    "Agri-PV Qualität": {
      "keyword": "Agri-PV Qualität",
      "position": 4,
      "previousPosition": 3,
      "searchVolume": 773,
      "competition": 21,
      "difficulty": 20,
      "opportunityScore": 1885,
      "category": "competitive",
      "intent": "mixed",
      "segment": "agri-pv",
      "lastUpdated": "2025-10-18T06:08:31.519Z"
    },
    "Agri-PV Wirtschaftlichkeit": {
      "keyword": "Agri-PV Wirtschaftlichkeit",
      "position": 9,
      "previousPosition": 7,
      "searchVolume": 964,
      "competition": 28,
      "difficulty": 24,
      "opportunityScore": 1854,
      "category": "technical",
      "intent": "mixed",
      "segment": "agri-pv",
      "lastUpdated": "2025-10-18T06:08:31.519Z"
    },
    "Batteriespeicher Eigenheim": {
      "keyword": "Batteriespeicher Eigenheim",
      "position": 1,
      "previousPosition": 1,
      "searchVolume": 2200,
      "competition": 64,
      "difficulty": 56,
      "opportunityScore": 1833,
      "category": "residential_installation",
      "intent": "mixed",
      "segment": "residential",
      "lastUpdated": "2025-10-18T06:08:31.519Z"
    },
    "Photovoltaik Eigenheimbesitzer": {
      "keyword": "Photovoltaik Eigenheimbesitzer",
      "position": 10,
      "previousPosition": 10,
      "searchVolume": 1900,
      "competition": 60,
      "difficulty": 48,
      "opportunityScore": 1759,
      "category": "seed",
      "intent": "mixed",
      "segment": "residential",
      "lastUpdated": "2025-10-18T06:08:31.519Z"
    },
    "Batteriespeicher Förderung 2025": {
      "keyword": "Batteriespeicher Förderung 2025",
      "position": 5,
      "previousPosition": 3,
      "searchVolume": 2000,
      "competition": 66,
      "difficulty": 52,
      "opportunityScore": 1695,
      "category": "storage",
      "intent": "informational",
      "segment": "storage",
      "lastUpdated": "2025-10-18T06:08:31.519Z"
    },
    "Solaranlage Eigenheim Förderung": {
      "keyword": "Solaranlage Eigenheim Förderung",
      "position": 3,
      "previousPosition": 2,
      "searchVolume": 1800,
      "competition": 62,
      "difficulty": 50,
      "opportunityScore": 1607,
      "category": "residential",
      "intent": "informational",
      "segment": "residential",
      "lastUpdated": "2025-10-18T06:08:31.519Z"
    },
    "Photovoltaik Finanzierung Eigenheim": {
      "keyword": "Photovoltaik Finanzierung Eigenheim",
      "position": 10,
      "previousPosition": 11,
      "searchVolume": 1600,
      "competition": 55,
      "difficulty": 48,
      "opportunityScore": 1553,
      "category": "residential_financing",
      "intent": "mixed",
      "segment": "residential",
      "lastUpdated": "2025-10-18T06:08:31.519Z"
    },
    "Agri-PV Hopfenanbau": {
      "keyword": "Agri-PV Hopfenanbau",
      "position": 1,
      "previousPosition": 1,
      "searchVolume": 947,
      "competition": 33,
      "difficulty": 28,
      "opportunityScore": 1552,
      "category": "applications",
      "intent": "mixed",
      "segment": "agri-pv",
      "lastUpdated": "2025-10-18T06:08:31.519Z"
    },
    "Agri-PV Förderungen 2025": {
      "keyword": "Agri-PV Förderungen 2025",
      "position": 9,
      "previousPosition": 9,
      "searchVolume": 1030,
      "competition": 45,
      "difficulty": 22,
      "opportunityScore": 1537,
      "category": "longtail",
      "intent": "informational",
      "segment": "agri-pv",
      "lastUpdated": "2025-10-18T06:08:31.519Z"
    },
    "Wallbox Photovoltaik Eigenheim": {
      "keyword": "Wallbox Photovoltaik Eigenheim",
      "position": 24,
      "previousPosition": 21,
      "searchVolume": 1400,
      "competition": 52,
      "difficulty": 44,
      "opportunityScore": 1458,
      "category": "residential_installation",
      "intent": "mixed",
      "segment": "residential",
      "lastUpdated": "2025-10-18T06:08:31.519Z"
    },
    "Solaranlage Eigenheim Planung": {
      "keyword": "Solaranlage Eigenheim Planung",
      "position": 8,
      "previousPosition": 8,
      "searchVolume": 1500,
      "competition": 55,
      "difficulty": 48,
      "opportunityScore": 1456,
      "category": "residential",
      "intent": "transactional",
      "segment": "residential",
      "lastUpdated": "2025-10-18T06:08:31.519Z"
    },
    "Agri-PV Planung": {
      "keyword": "Agri-PV Planung",
      "position": 7,
      "previousPosition": 6,
      "searchVolume": 950,
      "competition": 21,
      "difficulty": 46,
      "opportunityScore": 1418,
      "category": "technical",
      "intent": "transactional",
      "segment": "agri-pv",
      "lastUpdated": "2025-10-18T06:08:31.519Z"
    },
    "Agri-PV Naturschutz": {
      "keyword": "Agri-PV Naturschutz",
      "position": 11,
      "previousPosition": 12,
      "searchVolume": 1098,
      "competition": 27,
      "difficulty": 52,
      "opportunityScore": 1390,
      "category": "legal",
      "intent": "mixed",
      "segment": "agri-pv",
      "lastUpdated": "2025-10-18T06:08:31.519Z"
    },
    "KfW Förderung Photovoltaik Eigenheim": {
      "keyword": "KfW Förderung Photovoltaik Eigenheim",
      "position": 8,
      "previousPosition": 8,
      "searchVolume": 1500,
      "competition": 58,
      "difficulty": 50,
      "opportunityScore": 1389,
      "category": "residential_financing",
      "intent": "informational",
      "segment": "residential",
      "lastUpdated": "2025-10-18T06:08:31.519Z"
    },
    "Agri-PV Tierhaltung": {
      "keyword": "Agri-PV Tierhaltung",
      "position": 12,
      "previousPosition": 12,
      "searchVolume": 845,
      "competition": 39,
      "difficulty": 24,
      "opportunityScore": 1341,
      "category": "applications",
      "intent": "mixed",
      "segment": "agri-pv",
      "lastUpdated": "2025-10-18T06:08:31.519Z"
    },
    "Photovoltaik Einfamilienhaus Erfahrungen": {
      "keyword": "Photovoltaik Einfamilienhaus Erfahrungen",
      "position": 5,
      "previousPosition": 5,
      "searchVolume": 1300,
      "competition": 54,
      "difficulty": 44,
      "opportunityScore": 1327,
      "category": "residential",
      "intent": "comparison",
      "segment": "residential",
      "lastUpdated": "2025-10-18T06:08:31.519Z"
    },
    "Heimspeicher Vergleich": {
      "keyword": "Heimspeicher Vergleich",
      "position": 5,
      "previousPosition": 3,
      "searchVolume": 1500,
      "competition": 63,
      "difficulty": 50,
      "opportunityScore": 1327,
      "category": "storage",
      "intent": "comparison",
      "segment": "storage",
      "lastUpdated": "2025-10-18T06:08:31.519Z"
    },
    "Photovoltaik Installation Dach": {
      "keyword": "Photovoltaik Installation Dach",
      "position": 8,
      "previousPosition": 9,
      "searchVolume": 1400,
      "competition": 57,
      "difficulty": 49,
      "opportunityScore": 1321,
      "category": "residential_installation",
      "intent": "transactional",
      "segment": "residential",
      "lastUpdated": "2025-10-18T06:08:31.519Z"
    },
    "Agri Photovoltaik": {
      "keyword": "Agri Photovoltaik",
      "position": 20,
      "previousPosition": 19,
      "searchVolume": 1800,
      "competition": 65,
      "difficulty": 72,
      "opportunityScore": 1314,
      "category": "seed",
      "intent": "mixed",
      "segment": "agri-pv",
      "lastUpdated": "2025-10-18T06:08:31.519Z"
    },
    "Photovoltaik Eigenheim Rendite": {
      "keyword": "Photovoltaik Eigenheim Rendite",
      "position": 19,
      "previousPosition": 17,
      "searchVolume": 1300,
      "competition": 53,
      "difficulty": 46,
      "opportunityScore": 1313,
      "category": "residential_financing",
      "intent": "mixed",
      "segment": "residential",
      "lastUpdated": "2025-10-18T06:08:31.519Z"
    },
    "Agri-PV Biogas": {
      "keyword": "Agri-PV Biogas",
      "position": 24,
      "previousPosition": 21,
      "searchVolume": 1065,
      "competition": 38,
      "difficulty": 45,
      "opportunityScore": 1283,
      "category": "applications",
      "intent": "mixed",
      "segment": "agri-pv",
      "lastUpdated": "2025-10-18T06:08:31.519Z"
    },
    "Agri-PV Erfahrungen": {
      "keyword": "Agri-PV Erfahrungen",
      "position": 13,
      "previousPosition": 13,
      "searchVolume": 650,
      "competition": 21,
      "difficulty": 30,
      "opportunityScore": 1275,
      "category": "competitive",
      "intent": "comparison",
      "segment": "agri-pv",
      "lastUpdated": "2025-10-18T06:08:31.519Z"
    },
    "Beste Agri-PV Anbieter": {
      "keyword": "Beste Agri-PV Anbieter",
      "position": 24,
      "previousPosition": 22,
      "searchVolume": 695,
      "competition": 27,
      "difficulty": 28,
      "opportunityScore": 1264,
      "category": "competitive",
      "intent": "comparison",
      "segment": "agri-pv",
      "lastUpdated": "2025-10-18T06:08:31.519Z"
    },
    "Solaranlage Eigenheim Installation": {
      "keyword": "Solaranlage Eigenheim Installation",
      "position": 7,
      "previousPosition": 7,
      "searchVolume": 1200,
      "competition": 52,
      "difficulty": 46,
      "opportunityScore": 1224,
      "category": "residential",
      "intent": "transactional",
      "segment": "residential",
      "lastUpdated": "2025-10-18T06:08:31.519Z"
    },
    "Solaranlage Landwirtschaft": {
      "keyword": "Solaranlage Landwirtschaft",
      "position": 21,
      "previousPosition": 23,
      "searchVolume": 1600,
      "competition": 70,
      "difficulty": 65,
      "opportunityScore": 1185,
      "category": "seed",
      "intent": "mixed",
      "segment": "agri-pv",
      "lastUpdated": "2025-10-18T06:08:31.519Z"
    },
    "PV Anlage Notstrom": {
      "keyword": "PV Anlage Notstrom",
      "position": 22,
      "previousPosition": 23,
      "searchVolume": 1250,
      "competition": 59,
      "difficulty": 50,
      "opportunityScore": 1147,
      "category": "residential_installation",
      "intent": "mixed",
      "segment": "general",
      "lastUpdated": "2025-10-18T06:08:31.519Z"
    },
    "Batteriespeicher Kosten 10kWh": {
      "keyword": "Batteriespeicher Kosten 10kWh",
      "position": 13,
      "previousPosition": 15,
      "searchVolume": 1200,
      "competition": 60,
      "difficulty": 48,
      "opportunityScore": 1111,
      "category": "storage",
      "intent": "commercial",
      "segment": "storage",
      "lastUpdated": "2025-10-18T06:08:31.519Z"
    },
    "Stromspeicher Förderung Eigenheim": {
      "keyword": "Stromspeicher Förderung Eigenheim",
      "position": 19,
      "previousPosition": 20,
      "searchVolume": 1050,
      "competition": 52,
      "difficulty": 44,
      "opportunityScore": 1094,
      "category": "residential_financing",
      "intent": "informational",
      "segment": "residential",
      "lastUpdated": "2025-10-18T06:08:31.519Z"
    },
    "BAFA Zuschuss Photovoltaik Haus": {
      "keyword": "BAFA Zuschuss Photovoltaik Haus",
      "position": 14,
      "previousPosition": 11,
      "searchVolume": 1100,
      "competition": 54,
      "difficulty": 47,
      "opportunityScore": 1089,
      "category": "residential_financing",
      "intent": "mixed",
      "segment": "residential",
      "lastUpdated": "2025-10-18T06:08:31.519Z"
    },
    "Agri-PV für Landwirte": {
      "keyword": "Agri-PV für Landwirte",
      "position": 8,
      "previousPosition": 6,
      "searchVolume": 1090,
      "competition": 47,
      "difficulty": 56,
      "opportunityScore": 1058,
      "category": "longtail",
      "intent": "mixed",
      "segment": "agri-pv",
      "lastUpdated": "2025-10-18T06:08:31.519Z"
    },
    "Solaranlage Reihenhaus": {
      "keyword": "Solaranlage Reihenhaus",
      "position": 5,
      "previousPosition": 7,
      "searchVolume": 950,
      "competition": 47,
      "difficulty": 43,
      "opportunityScore": 1056,
      "category": "seed",
      "intent": "mixed",
      "segment": "residential",
      "lastUpdated": "2025-10-18T06:08:31.519Z"
    },
    "Photovoltaik Kredit Vergleich": {
      "keyword": "Photovoltaik Kredit Vergleich",
      "position": 16,
      "previousPosition": 16,
      "searchVolume": 1200,
      "competition": 60,
      "difficulty": 54,
      "opportunityScore": 1053,
      "category": "residential_financing",
      "intent": "comparison",
      "segment": "general",
      "lastUpdated": "2025-10-18T06:08:31.519Z"
    },
    "Smart Home Photovoltaik": {
      "keyword": "Smart Home Photovoltaik",
      "position": 14,
      "previousPosition": 13,
      "searchVolume": 950,
      "competition": 50,
      "difficulty": 42,
      "opportunityScore": 1033,
      "category": "residential_installation",
      "intent": "mixed",
      "segment": "general",
      "lastUpdated": "2025-10-18T06:08:31.519Z"
    },
    "Solaranlage Dachneigung": {
      "keyword": "Solaranlage Dachneigung",
      "position": 22,
      "previousPosition": 20,
      "searchVolume": 980,
      "competition": 50,
      "difficulty": 45,
      "opportunityScore": 1032,
      "category": "residential_installation",
      "intent": "mixed",
      "segment": "residential",
      "lastUpdated": "2025-10-18T06:08:31.519Z"
    },
    "Photovoltaik und Ackerbau gleichzeitig": {
      "keyword": "Photovoltaik und Ackerbau gleichzeitig",
      "position": 9,
      "previousPosition": 11,
      "searchVolume": 1032,
      "competition": 44,
      "difficulty": 56,
      "opportunityScore": 1032,
      "category": "longtail",
      "intent": "mixed",
      "segment": "agri-pv",
      "lastUpdated": "2025-10-18T06:08:31.519Z"
    },
    "Agri-PV Referenzen": {
      "keyword": "Agri-PV Referenzen",
      "position": 14,
      "previousPosition": 12,
      "searchVolume": 860,
      "competition": 36,
      "difficulty": 48,
      "opportunityScore": 1024,
      "category": "competitive",
      "intent": "mixed",
      "segment": "agri-pv",
      "lastUpdated": "2025-10-18T06:08:31.519Z"
    },
    "Agri-PV Rendite": {
      "keyword": "Agri-PV Rendite",
      "position": 16,
      "previousPosition": 16,
      "searchVolume": 952,
      "competition": 43,
      "difficulty": 52,
      "opportunityScore": 1002,
      "category": "technical",
      "intent": "mixed",
      "segment": "agri-pv",
      "lastUpdated": "2025-10-18T06:08:31.519Z"
    },
    "Photovoltaik steuerliche Vorteile Eigenheim": {
      "keyword": "Photovoltaik steuerliche Vorteile Eigenheim",
      "position": 26,
      "previousPosition": 24,
      "searchVolume": 980,
      "competition": 52,
      "difficulty": 46,
      "opportunityScore": 1000,
      "category": "residential_financing",
      "intent": "mixed",
      "segment": "residential",
      "lastUpdated": "2025-10-18T06:08:31.519Z"
    },
    "Photovoltaik Dachsanierung": {
      "keyword": "Photovoltaik Dachsanierung",
      "position": 29,
      "previousPosition": 28,
      "searchVolume": 900,
      "competition": 49,
      "difficulty": 42,
      "opportunityScore": 989,
      "category": "residential",
      "intent": "mixed",
      "segment": "residential",
      "lastUpdated": "2025-10-18T06:08:31.519Z"
    },
    "Agri-PV Förderung": {
      "keyword": "Agri-PV Förderung",
      "position": 12,
      "previousPosition": 11,
      "searchVolume": 1600,
      "competition": 80,
      "difficulty": 82,
      "opportunityScore": 988,
      "category": "technical",
      "intent": "informational",
      "segment": "agri-pv",
      "lastUpdated": "2025-10-18T06:08:31.519Z"
    },
    "Solaranlage Dachlast": {
      "keyword": "Solaranlage Dachlast",
      "position": 10,
      "previousPosition": 9,
      "searchVolume": 860,
      "competition": 48,
      "difficulty": 43,
      "opportunityScore": 945,
      "category": "residential_installation",
      "intent": "mixed",
      "segment": "residential",
      "lastUpdated": "2025-10-18T06:08:31.519Z"
    },
    "Agri-PV Obstplantage": {
      "keyword": "Agri-PV Obstplantage",
      "position": 39,
      "previousPosition": 36,
      "searchVolume": 709,
      "competition": 24,
      "difficulty": 51,
      "opportunityScore": 945,
      "category": "applications",
      "intent": "mixed",
      "segment": "agri-pv",
      "lastUpdated": "2025-10-18T06:08:31.519Z"
    },
    "Batteriespeicher Nachrüstung": {
      "keyword": "Batteriespeicher Nachrüstung",
      "position": 18,
      "previousPosition": 17,
      "searchVolume": 980,
      "competition": 58,
      "difficulty": 46,
      "opportunityScore": 942,
      "category": "storage",
      "intent": "mixed",
      "segment": "storage",
      "lastUpdated": "2025-10-18T06:08:31.519Z"
    },
    "Photovoltaik Ziegeldach": {
      "keyword": "Photovoltaik Ziegeldach",
      "position": 20,
      "previousPosition": 22,
      "searchVolume": 780,
      "competition": 46,
      "difficulty": 40,
      "opportunityScore": 907,
      "category": "residential",
      "intent": "mixed",
      "segment": "residential",
      "lastUpdated": "2025-10-18T06:08:31.519Z"
    },
    "Agri-PV Baden-Württemberg": {
      "keyword": "Agri-PV Baden-Württemberg",
      "position": 35,
      "previousPosition": 37,
      "searchVolume": 865,
      "competition": 37,
      "difficulty": 59,
      "opportunityScore": 901,
      "category": "regional",
      "intent": "mixed",
      "segment": "agri-pv",
      "lastUpdated": "2025-10-18T06:08:31.519Z"
    },
    "PV Speicher Dimensionierung": {
      "keyword": "PV Speicher Dimensionierung",
      "position": 36,
      "previousPosition": 37,
      "searchVolume": 860,
      "competition": 52,
      "difficulty": 45,
      "opportunityScore": 887,
      "category": "storage",
      "intent": "mixed",
      "segment": "storage",
      "lastUpdated": "2025-10-18T06:08:31.519Z"
    },
    "PV Anlage Bauernhof": {
      "keyword": "PV Anlage Bauernhof",
      "position": 16,
      "previousPosition": 16,
      "searchVolume": 880,
      "competition": 55,
      "difficulty": 45,
      "opportunityScore": 880,
      "category": "seed",
      "intent": "mixed",
      "segment": "agri-pv",
      "lastUpdated": "2025-10-18T06:08:31.519Z"
    },
    "Solaranlage Wartung Eigenheim": {
      "keyword": "Solaranlage Wartung Eigenheim",
      "position": 28,
      "previousPosition": 29,
      "searchVolume": 690,
      "competition": 42,
      "difficulty": 38,
      "opportunityScore": 863,
      "category": "residential_installation",
      "intent": "mixed",
      "segment": "residential",
      "lastUpdated": "2025-10-18T06:08:31.519Z"
    },
    "Solaranlage Berlin Eigenheim": {
      "keyword": "Solaranlage Berlin Eigenheim",
      "position": 27,
      "previousPosition": 24,
      "searchVolume": 880,
      "competition": 57,
      "difficulty": 45,
      "opportunityScore": 863,
      "category": "regional_residential",
      "intent": "mixed",
      "segment": "residential",
      "lastUpdated": "2025-10-18T06:08:31.519Z"
    },
    "Photovoltaik Zählerschrank Umbau": {
      "keyword": "Photovoltaik Zählerschrank Umbau",
      "position": 18,
      "previousPosition": 18,
      "searchVolume": 740,
      "competition": 46,
      "difficulty": 42,
      "opportunityScore": 841,
      "category": "residential_installation",
      "intent": "mixed",
      "segment": "general",
      "lastUpdated": "2025-10-18T06:08:31.519Z"
    },
    "Agri-PV Fördermittel": {
      "keyword": "Agri-PV Fördermittel",
      "position": 30,
      "previousPosition": 31,
      "searchVolume": 662,
      "competition": 24,
      "difficulty": 56,
      "opportunityScore": 828,
      "category": "legal",
      "intent": "mixed",
      "segment": "agri-pv",
      "lastUpdated": "2025-10-18T06:08:31.519Z"
    },
    "Solarpark Landwirtschaft": {
      "keyword": "Solarpark Landwirtschaft",
      "position": 14,
      "previousPosition": 16,
      "searchVolume": 590,
      "competition": 52,
      "difficulty": 20,
      "opportunityScore": 819,
      "category": "seed",
      "intent": "mixed",
      "segment": "agri-pv",
      "lastUpdated": "2025-10-18T06:08:31.519Z"
    },
    "Agri-PV Kosten": {
      "keyword": "Agri-PV Kosten",
      "position": 18,
      "previousPosition": 20,
      "searchVolume": 1200,
      "competition": 75,
      "difficulty": 75,
      "opportunityScore": 800,
      "category": "technical",
      "intent": "commercial",
      "segment": "agri-pv",
      "lastUpdated": "2025-10-18T06:08:31.519Z"
    },
    "Solaranlage Leasing Eigenheim": {
      "keyword": "Solaranlage Leasing Eigenheim",
      "position": 32,
      "previousPosition": 34,
      "searchVolume": 720,
      "competition": 48,
      "difficulty": 45,
      "opportunityScore": 774,
      "category": "residential_financing",
      "intent": "mixed",
      "segment": "residential",
      "lastUpdated": "2025-10-18T06:08:31.519Z"
    },
    "Notstromfähig Batteriespeicher": {
      "keyword": "Notstromfähig Batteriespeicher",
      "position": 15,
      "previousPosition": 12,
      "searchVolume": 720,
      "competition": 50,
      "difficulty": 44,
      "opportunityScore": 766,
      "category": "storage",
      "intent": "mixed",
      "segment": "storage",
      "lastUpdated": "2025-10-18T06:08:31.519Z"
    },
    "Agri-PV Baurecht": {
      "keyword": "Agri-PV Baurecht",
      "position": 26,
      "previousPosition": 23,
      "searchVolume": 963,
      "competition": 65,
      "difficulty": 62,
      "opportunityScore": 758,
      "category": "legal",
      "intent": "mixed",
      "segment": "agri-pv",
      "lastUpdated": "2025-10-18T06:08:31.519Z"
    },
    "Solarstrom Mietkauf": {
      "keyword": "Solarstrom Mietkauf",
      "position": 26,
      "previousPosition": 25,
      "searchVolume": 680,
      "competition": 46,
      "difficulty": 44,
      "opportunityScore": 756,
      "category": "residential_financing",
      "intent": "mixed",
      "segment": "general",
      "lastUpdated": "2025-10-18T06:08:31.519Z"
    },
    "Photovoltaik München Haus": {
      "keyword": "Photovoltaik München Haus",
      "position": 13,
      "previousPosition": 13,
      "searchVolume": 760,
      "competition": 55,
      "difficulty": 46,
      "opportunityScore": 752,
      "category": "regional_residential",
      "intent": "mixed",
      "segment": "residential",
      "lastUpdated": "2025-10-18T06:08:31.519Z"
    },
    "Agri-PV Wartung": {
      "keyword": "Agri-PV Wartung",
      "position": 25,
      "previousPosition": 26,
      "searchVolume": 869,
      "competition": 49,
      "difficulty": 67,
      "opportunityScore": 749,
      "category": "technical",
      "intent": "mixed",
      "segment": "agri-pv",
      "lastUpdated": "2025-10-18T06:08:31.519Z"
    },
    "Solaranlage Hamburg Dach": {
      "keyword": "Solaranlage Hamburg Dach",
      "position": 19,
      "previousPosition": 17,
      "searchVolume": 720,
      "competition": 53,
      "difficulty": 44,
      "opportunityScore": 742,
      "category": "regional_residential",
      "intent": "mixed",
      "segment": "residential",
      "lastUpdated": "2025-10-18T06:08:31.519Z"
    },
    "Doppelnutzung Solaranlage Vorteile": {
      "keyword": "Doppelnutzung Solaranlage Vorteile",
      "position": 30,
      "previousPosition": 27,
      "searchVolume": 562,
      "competition": 23,
      "difficulty": 53,
      "opportunityScore": 739,
      "category": "longtail",
      "intent": "mixed",
      "segment": "general",
      "lastUpdated": "2025-10-18T06:08:31.519Z"
    },
    "Photovoltaik Flachdach Eigenheim": {
      "keyword": "Photovoltaik Flachdach Eigenheim",
      "position": 38,
      "previousPosition": 38,
      "searchVolume": 620,
      "competition": 45,
      "difficulty": 39,
      "opportunityScore": 738,
      "category": "residential",
      "intent": "mixed",
      "segment": "residential",
      "lastUpdated": "2025-10-18T06:08:31.519Z"
    },
    "Photovoltaik Köln Einfamilienhaus": {
      "keyword": "Photovoltaik Köln Einfamilienhaus",
      "position": 28,
      "previousPosition": 30,
      "searchVolume": 680,
      "competition": 51,
      "difficulty": 43,
      "opportunityScore": 723,
      "category": "regional_residential",
      "intent": "mixed",
      "segment": "residential",
      "lastUpdated": "2025-10-18T06:08:31.519Z"
    },
    "Agri-PV Gemüseanbau": {
      "keyword": "Agri-PV Gemüseanbau",
      "position": 33,
      "previousPosition": 30,
      "searchVolume": 1030,
      "competition": 70,
      "difficulty": 78,
      "opportunityScore": 696,
      "category": "applications",
      "intent": "mixed",
      "segment": "agri-pv",
      "lastUpdated": "2025-10-18T06:08:31.519Z"
    },
    "Solaranlage Leipzig Eigenheim": {
      "keyword": "Solaranlage Leipzig Eigenheim",
      "position": 16,
      "previousPosition": 14,
      "searchVolume": 610,
      "competition": 48,
      "difficulty": 42,
      "opportunityScore": 678,
      "category": "regional_residential",
      "intent": "mixed",
      "segment": "residential",
      "lastUpdated": "2025-10-18T06:08:31.519Z"
    },
    "Solaranlage Frankfurt Eigenheim": {
      "keyword": "Solaranlage Frankfurt Eigenheim",
      "position": 38,
      "previousPosition": 37,
      "searchVolume": 650,
      "competition": 52,
      "difficulty": 44,
      "opportunityScore": 677,
      "category": "regional_residential",
      "intent": "mixed",
      "segment": "residential",
      "lastUpdated": "2025-10-18T06:08:31.519Z"
    },
    "Photovoltaik Stuttgart Haus": {
      "keyword": "Photovoltaik Stuttgart Haus",
      "position": 12,
      "previousPosition": 14,
      "searchVolume": 630,
      "competition": 50,
      "difficulty": 43,
      "opportunityScore": 677,
      "category": "regional_residential",
      "intent": "mixed",
      "segment": "residential",
      "lastUpdated": "2025-10-18T06:08:31.519Z"
    },
    "Agri-PV Bayern": {
      "keyword": "Agri-PV Bayern",
      "position": 12,
      "previousPosition": 9,
      "searchVolume": 650,
      "competition": 55,
      "difficulty": 42,
      "opportunityScore": 670,
      "category": "regional",
      "intent": "mixed",
      "segment": "agri-pv",
      "lastUpdated": "2025-10-18T06:08:31.519Z"
    },
    "Photovoltaik Hannover Dach": {
      "keyword": "Photovoltaik Hannover Dach",
      "position": 34,
      "previousPosition": 32,
      "searchVolume": 590,
      "competition": 47,
      "difficulty": 41,
      "opportunityScore": 670,
      "category": "regional_residential",
      "intent": "mixed",
      "segment": "residential",
      "lastUpdated": "2025-10-18T06:08:31.519Z"
    },
    "Solaranlage Doppelhaus": {
      "keyword": "Solaranlage Doppelhaus",
      "position": 10,
      "previousPosition": 11,
      "searchVolume": 540,
      "competition": 44,
      "difficulty": 38,
      "opportunityScore": 659,
      "category": "residential",
      "intent": "mixed",
      "segment": "residential",
      "lastUpdated": "2025-10-18T06:08:31.519Z"
    },
    "Photovoltaik Abschreibung Privat": {
      "keyword": "Photovoltaik Abschreibung Privat",
      "position": 12,
      "previousPosition": 13,
      "searchVolume": 560,
      "competition": 45,
      "difficulty": 40,
      "opportunityScore": 659,
      "category": "residential_financing",
      "intent": "mixed",
      "segment": "residential",
      "lastUpdated": "2025-10-18T06:08:31.519Z"
    },
    "Solaranlage Nürnberg Hausdach": {
      "keyword": "Solaranlage Nürnberg Hausdach",
      "position": 28,
      "previousPosition": 25,
      "searchVolume": 560,
      "competition": 46,
      "difficulty": 40,
      "opportunityScore": 651,
      "category": "regional_residential",
      "intent": "mixed",
      "segment": "residential",
      "lastUpdated": "2025-10-18T06:08:31.519Z"
    },
    "Photovoltaik Dresden Eigenheim": {
      "keyword": "Photovoltaik Dresden Eigenheim",
      "position": 39,
      "previousPosition": 36,
      "searchVolume": 540,
      "competition": 45,
      "difficulty": 39,
      "opportunityScore": 643,
      "category": "regional_residential",
      "intent": "mixed",
      "segment": "residential",
      "lastUpdated": "2025-10-18T06:08:31.519Z"
    },
    "Lithium vs Salzbatterie": {
      "keyword": "Lithium vs Salzbatterie",
      "position": 16,
      "previousPosition": 13,
      "searchVolume": 550,
      "competition": 46,
      "difficulty": 40,
      "opportunityScore": 640,
      "category": "storage",
      "intent": "mixed",
      "segment": "storage",
      "lastUpdated": "2025-10-18T06:08:31.519Z"
    },
    "Agri-PV Mecklenburg-Vorpommern": {
      "keyword": "Agri-PV Mecklenburg-Vorpommern",
      "position": 29,
      "previousPosition": 29,
      "searchVolume": 618,
      "competition": 40,
      "difficulty": 58,
      "opportunityScore": 631,
      "category": "regional",
      "intent": "mixed",
      "segment": "agri-pv",
      "lastUpdated": "2025-10-18T06:08:31.519Z"
    },
    "Agri-PV Beratung": {
      "keyword": "Agri-PV Beratung",
      "position": 38,
      "previousPosition": 38,
      "searchVolume": 764,
      "competition": 49,
      "difficulty": 73,
      "opportunityScore": 626,
      "category": "competitive",
      "intent": "transactional",
      "segment": "agri-pv",
      "lastUpdated": "2025-10-18T06:08:31.519Z"
    },
    "Agri-PV Niedersachsen": {
      "keyword": "Agri-PV Niedersachsen",
      "position": 20,
      "previousPosition": 21,
      "searchVolume": 644,
      "competition": 28,
      "difficulty": 75,
      "opportunityScore": 625,
      "category": "regional",
      "intent": "mixed",
      "segment": "agri-pv",
      "lastUpdated": "2025-10-18T06:08:31.519Z"
    },
    "Photovoltaik Agrar": {
      "keyword": "Photovoltaik Agrar",
      "position": 13,
      "previousPosition": 15,
      "searchVolume": 720,
      "competition": 60,
      "difficulty": 58,
      "opportunityScore": 610,
      "category": "seed",
      "intent": "mixed",
      "segment": "general",
      "lastUpdated": "2025-10-18T06:08:31.519Z"
    },
    "Second Life Speicher": {
      "keyword": "Second Life Speicher",
      "position": 39,
      "previousPosition": 41,
      "searchVolume": 500,
      "competition": 44,
      "difficulty": 38,
      "opportunityScore": 610,
      "category": "storage",
      "intent": "mixed",
      "segment": "storage",
      "lastUpdated": "2025-10-18T06:08:31.519Z"
    },
    "Agri-PV Brandenburg": {
      "keyword": "Agri-PV Brandenburg",
      "position": 14,
      "previousPosition": 15,
      "searchVolume": 480,
      "competition": 45,
      "difficulty": 35,
      "opportunityScore": 600,
      "category": "regional",
      "intent": "mixed",
      "segment": "agri-pv",
      "lastUpdated": "2025-10-18T06:08:31.519Z"
    },
    "Agri-PV Nordrhein-Westfalen": {
      "keyword": "Agri-PV Nordrhein-Westfalen",
      "position": 22,
      "previousPosition": 22,
      "searchVolume": 520,
      "competition": 50,
      "difficulty": 38,
      "opportunityScore": 591,
      "category": "regional",
      "intent": "mixed",
      "segment": "agri-pv",
      "lastUpdated": "2025-10-18T06:08:31.519Z"
    },
    "Agri-PV Genehmigung": {
      "keyword": "Agri-PV Genehmigung",
      "position": 13,
      "previousPosition": 10,
      "searchVolume": 664,
      "competition": 39,
      "difficulty": 80,
      "opportunityScore": 558,
      "category": "legal",
      "intent": "mixed",
      "segment": "agri-pv",
      "lastUpdated": "2025-10-18T06:08:31.519Z"
    },
    "Agri-PV KfW": {
      "keyword": "Agri-PV KfW",
      "position": 12,
      "previousPosition": 12,
      "searchVolume": 505,
      "competition": 66,
      "difficulty": 26,
      "opportunityScore": 549,
      "category": "legal",
      "intent": "mixed",
      "segment": "agri-pv",
      "lastUpdated": "2025-10-18T06:08:31.519Z"
    },
    "E3DC vs Sonnen": {
      "keyword": "E3DC vs Sonnen",
      "position": 35,
      "previousPosition": 34,
      "searchVolume": 450,
      "competition": 45,
      "difficulty": 39,
      "opportunityScore": 536,
      "category": "storage",
      "intent": "mixed",
      "segment": "general",
      "lastUpdated": "2025-10-18T06:08:31.519Z"
    },
    "Agri-PV Einspeisung": {
      "keyword": "Agri-PV Einspeisung",
      "position": 34,
      "previousPosition": 33,
      "searchVolume": 642,
      "competition": 53,
      "difficulty": 69,
      "opportunityScore": 526,
      "category": "technical",
      "intent": "mixed",
      "segment": "agri-pv",
      "lastUpdated": "2025-10-18T06:08:31.519Z"
    },
    "Agri-PV Gesetz": {
      "keyword": "Agri-PV Gesetz",
      "position": 28,
      "previousPosition": 25,
      "searchVolume": 780,
      "competition": 75,
      "difficulty": 76,
      "opportunityScore": 517,
      "category": "legal",
      "intent": "informational",
      "segment": "agri-pv",
      "lastUpdated": "2025-10-18T06:08:31.519Z"
    },
    "Agri-PV Gewächshaus": {
      "keyword": "Agri-PV Gewächshaus",
      "position": 13,
      "previousPosition": 12,
      "searchVolume": 546,
      "competition": 73,
      "difficulty": 34,
      "opportunityScore": 510,
      "category": "applications",
      "intent": "mixed",
      "segment": "agri-pv",
      "lastUpdated": "2025-10-18T06:08:31.519Z"
    },
    "Agri-PV Netzanschluss": {
      "keyword": "Agri-PV Netzanschluss",
      "position": 35,
      "previousPosition": 32,
      "searchVolume": 444,
      "competition": 43,
      "difficulty": 46,
      "opportunityScore": 499,
      "category": "technical",
      "intent": "mixed",
      "segment": "agri-pv",
      "lastUpdated": "2025-10-18T06:08:31.519Z"
    },
    "Agri-PV Anlagenplanung Schritt für Schritt": {
      "keyword": "Agri-PV Anlagenplanung Schritt für Schritt",
      "position": 34,
      "previousPosition": 35,
      "searchVolume": 352,
      "competition": 39,
      "difficulty": 38,
      "opportunityScore": 457,
      "category": "longtail",
      "intent": "transactional",
      "segment": "agri-pv",
      "lastUpdated": "2025-10-18T06:08:31.519Z"
    },
    "Agri-PV Forstwirtschaft": {
      "keyword": "Agri-PV Forstwirtschaft",
      "position": 36,
      "previousPosition": 38,
      "searchVolume": 389,
      "competition": 46,
      "difficulty": 41,
      "opportunityScore": 447,
      "category": "applications",
      "intent": "mixed",
      "segment": "agri-pv",
      "lastUpdated": "2025-10-18T06:08:31.519Z"
    },
    "Agri-PV Service": {
      "keyword": "Agri-PV Service",
      "position": 34,
      "previousPosition": 34,
      "searchVolume": 492,
      "competition": 35,
      "difficulty": 75,
      "opportunityScore": 447,
      "category": "competitive",
      "intent": "mixed",
      "segment": "agri-pv",
      "lastUpdated": "2025-10-18T06:08:31.519Z"
    },
    "Agri-PV EEG": {
      "keyword": "Agri-PV EEG",
      "position": 15,
      "previousPosition": 14,
      "searchVolume": 540,
      "competition": 39,
      "difficulty": 84,
      "opportunityScore": 439,
      "category": "legal",
      "intent": "informational",
      "segment": "agri-pv",
      "lastUpdated": "2025-10-18T06:08:31.519Z"
    },
    "Agri-PV Eigenverbrauch": {
      "keyword": "Agri-PV Eigenverbrauch",
      "position": 38,
      "previousPosition": 36,
      "searchVolume": 293,
      "competition": 25,
      "difficulty": 51,
      "opportunityScore": 386,
      "category": "technical",
      "intent": "mixed",
      "segment": "agri-pv",
      "lastUpdated": "2025-10-18T06:08:31.519Z"
    },
    "Agri-PV Hessen": {
      "keyword": "Agri-PV Hessen",
      "position": 26,
      "previousPosition": 28,
      "searchVolume": 364,
      "competition": 47,
      "difficulty": 50,
      "opportunityScore": 375,
      "category": "regional",
      "intent": "mixed",
      "segment": "agri-pv",
      "lastUpdated": "2025-10-18T06:08:31.519Z"
    },
    "Agrivoltaik": {
      "keyword": "Agrivoltaik",
      "position": 24,
      "previousPosition": 24,
      "searchVolume": 320,
      "competition": 25,
      "difficulty": 61,
      "opportunityScore": 372,
      "category": "seed",
      "intent": "mixed",
      "segment": "agri-pv",
      "lastUpdated": "2025-10-18T06:08:31.519Z"
    },
    "Agri-PV Versicherung": {
      "keyword": "Agri-PV Versicherung",
      "position": 17,
      "previousPosition": 16,
      "searchVolume": 457,
      "competition": 69,
      "difficulty": 54,
      "opportunityScore": 372,
      "category": "legal",
      "intent": "mixed",
      "segment": "agri-pv",
      "lastUpdated": "2025-10-18T06:08:31.519Z"
    },
    "Doppelnutzung Solar": {
      "keyword": "Doppelnutzung Solar",
      "position": 27,
      "previousPosition": 24,
      "searchVolume": 450,
      "competition": 65,
      "difficulty": 65,
      "opportunityScore": 346,
      "category": "seed",
      "intent": "mixed",
      "segment": "general",
      "lastUpdated": "2025-10-18T06:08:31.519Z"
    },
    "Agri-PV Ackerbau": {
      "keyword": "Agri-PV Ackerbau",
      "position": 20,
      "previousPosition": 22,
      "searchVolume": 380,
      "competition": 69,
      "difficulty": 42,
      "opportunityScore": 342,
      "category": "applications",
      "intent": "mixed",
      "segment": "agri-pv",
      "lastUpdated": "2025-10-18T06:08:31.519Z"
    },
    "Agri-PV Installation": {
      "keyword": "Agri-PV Installation",
      "position": 34,
      "previousPosition": 33,
      "searchVolume": 400,
      "competition": 68,
      "difficulty": 53,
      "opportunityScore": 331,
      "category": "technical",
      "intent": "transactional",
      "segment": "agri-pv",
      "lastUpdated": "2025-10-18T06:08:31.519Z"
    },
    "Agri-PV Weinbau": {
      "keyword": "Agri-PV Weinbau",
      "position": 19,
      "previousPosition": 21,
      "searchVolume": 289,
      "competition": 21,
      "difficulty": 67,
      "opportunityScore": 328,
      "category": "applications",
      "intent": "mixed",
      "segment": "agri-pv",
      "lastUpdated": "2025-10-18T06:08:31.519Z"
    },
    "Solaranlage Feld": {
      "keyword": "Solaranlage Feld",
      "position": 33,
      "previousPosition": 34,
      "searchVolume": 280,
      "competition": 66,
      "difficulty": 29,
      "opportunityScore": 295,
      "category": "seed",
      "intent": "mixed",
      "segment": "general",
      "lastUpdated": "2025-10-18T06:08:31.519Z"
    },
    "Kosten Nutzen Rechnung Agri-PV": {
      "keyword": "Kosten Nutzen Rechnung Agri-PV",
      "position": 13,
      "previousPosition": 13,
      "searchVolume": 265,
      "competition": 30,
      "difficulty": 60,
      "opportunityScore": 294,
      "category": "longtail",
      "intent": "commercial",
      "segment": "agri-pv",
      "lastUpdated": "2025-10-18T06:08:31.519Z"
    },
    "Wie funktioniert Agri-PV": {
      "keyword": "Wie funktioniert Agri-PV",
      "position": 34,
      "previousPosition": 33,
      "searchVolume": 257,
      "competition": 60,
      "difficulty": 32,
      "opportunityScore": 279,
      "category": "longtail",
      "intent": "informational",
      "segment": "agri-pv",
      "lastUpdated": "2025-10-18T06:08:31.519Z"
    },
    "Solaranlage mit Landwirtschaft kombinieren": {
      "keyword": "Solaranlage mit Landwirtschaft kombinieren",
      "position": 37,
      "previousPosition": 39,
      "searchVolume": 423,
      "competition": 70,
      "difficulty": 84,
      "opportunityScore": 275,
      "category": "longtail",
      "intent": "mixed",
      "segment": "agri-pv",
      "lastUpdated": "2025-10-18T06:08:31.519Z"
    },
    "Agri-PV Weidewirtschaft": {
      "keyword": "Agri-PV Weidewirtschaft",
      "position": 29,
      "previousPosition": 29,
      "searchVolume": 290,
      "competition": 47,
      "difficulty": 59,
      "opportunityScore": 274,
      "category": "applications",
      "intent": "mixed",
      "segment": "agri-pv",
      "lastUpdated": "2025-10-18T06:08:31.519Z"
    },
    "Agri-PV Vergleich": {
      "keyword": "Agri-PV Vergleich",
      "position": 27,
      "previousPosition": 27,
      "searchVolume": 244,
      "competition": 20,
      "difficulty": 81,
      "opportunityScore": 242,
      "category": "competitive",
      "intent": "comparison",
      "segment": "agri-pv",
      "lastUpdated": "2025-10-18T06:08:31.519Z"
    },
    "Agri-PV Rheinland-Pfalz": {
      "keyword": "Agri-PV Rheinland-Pfalz",
      "position": 33,
      "previousPosition": 34,
      "searchVolume": 305,
      "competition": 40,
      "difficulty": 88,
      "opportunityScore": 238,
      "category": "regional",
      "intent": "mixed",
      "segment": "agri-pv",
      "lastUpdated": "2025-10-18T06:08:31.519Z"
    },
    "Agri-PV Schleswig-Holstein": {
      "keyword": "Agri-PV Schleswig-Holstein",
      "position": 25,
      "previousPosition": 22,
      "searchVolume": 190,
      "competition": 20,
      "difficulty": 66,
      "opportunityScore": 221,
      "category": "regional",
      "intent": "mixed",
      "segment": "agri-pv",
      "lastUpdated": "2025-10-18T06:08:31.519Z"
    },
    "PV Freifläche Landwirt": {
      "keyword": "PV Freifläche Landwirt",
      "position": 16,
      "previousPosition": 14,
      "searchVolume": 210,
      "competition": 73,
      "difficulty": 23,
      "opportunityScore": 219,
      "category": "seed",
      "intent": "mixed",
      "segment": "agri-pv",
      "lastUpdated": "2025-10-18T06:08:31.519Z"
    },
    "Zukunft der Landwirtschaft mit Solar": {
      "keyword": "Zukunft der Landwirtschaft mit Solar",
      "position": 11,
      "previousPosition": 12,
      "searchVolume": 204,
      "competition": 25,
      "difficulty": 86,
      "opportunityScore": 184,
      "category": "longtail",
      "intent": "mixed",
      "segment": "agri-pv",
      "lastUpdated": "2025-10-18T06:08:31.519Z"
    },
    "Agri-PV Steuervorteile": {
      "keyword": "Agri-PV Steuervorteile",
      "position": 12,
      "previousPosition": 9,
      "searchVolume": 251,
      "competition": 64,
      "difficulty": 80,
      "opportunityScore": 174,
      "category": "legal",
      "intent": "mixed",
      "segment": "agri-pv",
      "lastUpdated": "2025-10-18T06:08:31.519Z"
    },
    "Agri-PV BAFA": {
      "keyword": "Agri-PV BAFA",
      "position": 13,
      "previousPosition": 13,
      "searchVolume": 114,
      "competition": 56,
      "difficulty": 28,
      "opportunityScore": 136,
      "category": "legal",
      "intent": "mixed",
      "segment": "agri-pv",
      "lastUpdated": "2025-10-18T06:08:31.519Z"
    },
    "Nachhaltige Landwirtschaft Solarenergie": {
      "keyword": "Nachhaltige Landwirtschaft Solarenergie",
      "position": 14,
      "previousPosition": 16,
      "searchVolume": 167,
      "competition": 67,
      "difficulty": 76,
      "opportunityScore": 117,
      "category": "longtail",
      "intent": "mixed",
      "segment": "agri-pv",
      "lastUpdated": "2025-10-18T06:08:31.519Z"
    },
    "Agri-PV Garantie": {
      "keyword": "Agri-PV Garantie",
      "position": 19,
      "previousPosition": 17,
      "searchVolume": 133,
      "competition": 69,
      "difficulty": 83,
      "opportunityScore": 88,
      "category": "competitive",
      "intent": "mixed",
      "segment": "agri-pv",
      "lastUpdated": "2025-10-18T06:08:31.519Z"
    },
    "Agri-PV Sachsen-Anhalt": {
      "keyword": "Agri-PV Sachsen-Anhalt",
      "position": 32,
      "previousPosition": 30,
      "searchVolume": 107,
      "competition": 50,
      "difficulty": 85,
      "opportunityScore": 79,
      "category": "regional",
      "intent": "mixed",
      "segment": "agri-pv",
      "lastUpdated": "2025-10-18T06:08:31.519Z"
    }
  },
  "alerts": [
    {
      "type": "loss",
      "severity": "error",
      "keyword": "Agri-PV Bayern",
      "segment": "agri-pv",
      "message": "\"Agri-PV Bayern\" fällt aus Top 10 heraus (Position 12)",
      "position": 12,
      "change": -3,
      "timestamp": "2025-10-18T06:08:31.532Z"
    },
    {
      "type": "loss",
      "severity": "error",
      "keyword": "Agri-PV Genehmigung",
      "segment": "agri-pv",
      "message": "\"Agri-PV Genehmigung\" fällt aus Top 10 heraus (Position 13)",
      "position": 13,
      "change": -3,
      "timestamp": "2025-10-18T06:08:31.532Z"
    },
    {
      "type": "loss",
      "severity": "error",
      "keyword": "Agri-PV Steuervorteile",
      "segment": "agri-pv",
      "message": "\"Agri-PV Steuervorteile\" fällt aus Top 10 heraus (Position 12)",
      "position": 12,
      "change": -3,
      "timestamp": "2025-10-18T06:08:31.532Z"
    },
    {
      "type": "milestone",
      "severity": "success",
      "keyword": "Wärmepumpe Photovoltaik Kombination",
      "segment": "sector-coupling",
      "message": "\"Wärmepumpe Photovoltaik Kombination\" erreicht Top 10 (Position 10)",
      "position": 10,
      "change": 2,
      "timestamp": "2025-10-18T06:08:31.531Z"
    },
    {
      "type": "milestone",
      "severity": "success",
      "keyword": "Photovoltaik Finanzierung Eigenheim",
      "segment": "residential",
      "message": "\"Photovoltaik Finanzierung Eigenheim\" erreicht Top 10 (Position 10)",
      "position": 10,
      "change": 1,
      "timestamp": "2025-10-18T06:08:31.531Z"
    },
    {
      "type": "milestone",
      "severity": "success",
      "keyword": "Photovoltaik und Ackerbau gleichzeitig",
      "segment": "agri-pv",
      "message": "\"Photovoltaik und Ackerbau gleichzeitig\" erreicht Top 10 (Position 9)",
      "position": 9,
      "change": 2,
      "timestamp": "2025-10-18T06:08:31.532Z"
    },
    {
      "type": "milestone",
      "severity": "success",
      "keyword": "Solaranlage Doppelhaus",
      "segment": "residential",
      "message": "\"Solaranlage Doppelhaus\" erreicht Top 10 (Position 10)",
      "position": 10,
      "change": 1,
      "timestamp": "2025-10-18T06:08:31.532Z"
    },
    {
      "type": "trend",
      "severity": "success",
      "message": "Top 10 Anteil verbessert (17.32% → 25.98%)",
      "timestamp": "2025-10-18T06:08:31.532Z"
    }
  ],
  "summary": {
    "totalKeywords": 127,
    "avgPosition": 18.97,
    "top10Percentage": 25.98,
    "estimatedTraffic": 14596,
    "alertCount": 8
  }
}